{"id": "MUS321H1F20199", "code": "MUS321H1F", "name": "The Beatles", "description": "In The Ultimate Encyclopedia Of Rock, it was written of the The Beatles that \u00e2\u20ac\u0153From three-minute pop classics to the psychedelic extravaganza of \u00e2\u20ac\u02dcSgt. Pepper\u00e2\u20ac\u2122, their songs soundtracked the Sixties. They were the greatest group in history. They probably always will be\u00e2\u20ac\u009d. In addition to a survey of the group\u00e2\u20ac\u2122s history, their recordings, and their films, this course aims to answer two basic questions: (1) what made the songs of The Beatles so successful? (2) in what ways did the band\u00e2\u20ac\u2122s artistic output \u00e2\u20ac\u0153soundtrack\u00e2\u20ac\u009d the 1960s? No prior background in music or ability to read music is required.", "division": "Faculty of Arts and Science", "department": "Faculty of Music", "prerequisites": "", "exclusions": "HMU111H1", "level": 300, "campus": "UTSG", "term": "2019 Fall", "breadths": [1], "meeting_sections": []}