{"id": "PSY311H5F20195F", "code": "PSY311H5F2", "name": "Social Development", "description": "A survey of contemporary research and theory in social development during infancy and childhood with consideration of the cultural context of development. Topics include interactional development, attachment, understanding self and others, sex role development, parenting and socialization, and outcome of development. [36L]", "division": "University of Toronto Mississauga", "department": "Psychology", "prerequisites": "PSY201H5/equivalent, PSY210H5", "exclusions": "PSY311H1/PSYC23H3", "level": 300, "campus": "UTM", "term": "2019 Summer F", "breadths": [], "meeting_sections": [{"code": "L0101", "instructors": ["S Kamenetsky"], "times": [{"day": "TUESDAY", "start": 36000, "end": 46800, "duration": 10800, "location": "IB 235"}, {"day": "THURSDAY", "start": 36000, "end": 46800, "duration": 10800, "location": "IB 235"}], "size": 100, "enrolment": 0}]}